aspose/__init__.py
aspose/pycore.cp310-win_amd64.pyd
aspose/pycore.cp311-win_amd64.pyd
aspose/pycore.cp312-win_amd64.pyd
aspose/pycore.cp313-win_amd64.pyd
aspose/pycore.cp35-win_amd64.pyd
aspose/pycore.cp36-win_amd64.pyd
aspose/pycore.cp37-win_amd64.pyd
aspose/pycore.cp38-win_amd64.pyd
aspose/pycore.cp39-win_amd64.pyd
aspose/pydrawing.cp310-win_amd64.pyd
aspose/pydrawing.cp311-win_amd64.pyd
aspose/pydrawing.cp312-win_amd64.pyd
aspose/pydrawing.cp313-win_amd64.pyd
aspose/pydrawing.cp35-win_amd64.pyd
aspose/pydrawing.cp36-win_amd64.pyd
aspose/pydrawing.cp37-win_amd64.pyd
aspose/pydrawing.cp38-win_amd64.pyd
aspose/pydrawing.cp39-win_amd64.pyd
aspose/pygc.cp310-win_amd64.pyd
aspose/pygc.cp311-win_amd64.pyd
aspose/pygc.cp312-win_amd64.pyd
aspose/pygc.cp313-win_amd64.pyd
aspose/pygc.cp35-win_amd64.pyd
aspose/pygc.cp36-win_amd64.pyd
aspose/pygc.cp37-win_amd64.pyd
aspose/pygc.cp38-win_amd64.pyd
aspose/pygc.cp39-win_amd64.pyd
aspose/pyio.cp310-win_amd64.pyd
aspose/pyio.cp311-win_amd64.pyd
aspose/pyio.cp312-win_amd64.pyd
aspose/pyio.cp313-win_amd64.pyd
aspose/pyio.cp35-win_amd64.pyd
aspose/pyio.cp36-win_amd64.pyd
aspose/pyio.cp37-win_amd64.pyd
aspose/pyio.cp38-win_amd64.pyd
aspose/pyio.cp39-win_amd64.pyd
aspose/pyreflection.cp310-win_amd64.pyd
aspose/pyreflection.cp311-win_amd64.pyd
aspose/pyreflection.cp312-win_amd64.pyd
aspose/pyreflection.cp313-win_amd64.pyd
aspose/pyreflection.cp35-win_amd64.pyd
aspose/pyreflection.cp36-win_amd64.pyd
aspose/pyreflection.cp37-win_amd64.pyd
aspose/pyreflection.cp38-win_amd64.pyd
aspose/pyreflection.cp39-win_amd64.pyd
aspose/slides.cp310-win_amd64.pyd
aspose/slides.cp311-win_amd64.pyd
aspose/slides.cp312-win_amd64.pyd
aspose/slides.cp313-win_amd64.pyd
aspose/slides.cp35-win_amd64.pyd
aspose/slides.cp36-win_amd64.pyd
aspose/slides.cp37-win_amd64.pyd
aspose/slides.cp38-win_amd64.pyd
aspose/slides.cp39-win_amd64.pyd
aspose/__pyinstaller/__init__.pyi
aspose/__pyinstaller/hook-aspose.py
aspose/assemblies/pycore/WrpInterop.Aspose.PyCore.dll
aspose_slides-25.12.0.dist-info/Aspose.Slides for Python via .NET.Agreements.pdf
aspose_slides-25.12.0.dist-info/Aspose_End-User-License-Agreement.md
aspose_slides-25.12.0.dist-info/METADATA
aspose_slides-25.12.0.dist-info/WHEEL
aspose_slides-25.12.0.dist-info/entry_points.txt
aspose_slides-25.12.0.dist-info/top_level.txt
aspose_slides-25.12.0.dist-info/RECORD
