Metadata-Version: 2.1
Name: aspose_slides
Version: 25.12.0
Summary: Aspose.Slides for Python via .NET is a presentation file formats processing library for working with Microsoft PowerPoint files without using Microsoft PowerPoint.
Home-page: https://products.aspose.com/slides/python-net/
Author: Aspose
License: https://about.aspose.com/legal/eula/
Project-URL: Docs, https://docs.aspose.com/slides/python-net/
Project-URL: Demos, https://products.aspose.com/slides/conversion/
Project-URL: API Reference, https://reference.aspose.com/slides/python-net/
Project-URL: Blog, https://blog.aspose.com/category/slides/
Project-URL: Search, https://search.aspose.com/
Project-URL: Free Support, https://forum.aspose.com/c/slides
Project-URL: Release Notes, https://releases.aspose.com/slides/python-net/release-notes/2025/aspose-slides-for-python-net-25-12-release-notes/
Project-URL: Temporary License, https://purchase.aspose.com/temporary-license
Keywords: ppt,pptx,potx,pot,pps,ppsx,odt,import,export,convert,edit,pdf,xps,swf,svg,html,html5,powerpoint,presentation
Platform: win_amd64
Classifier: Intended Audience :: Developers
Classifier: Intended Audience :: Education
Classifier: Intended Audience :: Information Technology
Classifier: License :: Other/Proprietary License
Classifier: License :: Free To Use But Restricted
Classifier: Operating System :: Microsoft :: Windows
Classifier: Operating System :: Unix
Classifier: Operating System :: MacOS
Classifier: Operating System :: POSIX
Classifier: Programming Language :: Python :: 3
Classifier: Programming Language :: Python :: 3 :: Only
Classifier: Programming Language :: Python :: 3.5
Classifier: Programming Language :: Python :: 3.6
Classifier: Programming Language :: Python :: 3.7
Classifier: Programming Language :: Python :: 3.8
Classifier: Programming Language :: Python :: 3.9
Classifier: Programming Language :: Python :: 3.10
Classifier: Programming Language :: Python :: 3.11
Classifier: Programming Language :: Python :: 3.12
Classifier: Programming Language :: Python :: 3.13
Classifier: Topic :: Software Development
Classifier: Topic :: Software Development :: Libraries
Classifier: Topic :: Office/Business
Classifier: Topic :: Office/Business :: Office Suites
Classifier: Topic :: Multimedia :: Graphics :: Presentation
Requires-Python: >=3.5,<3.14
License-File: Aspose.Slides for Python via .NET.Agreements.pdf
License-File: Aspose_End-User-License-Agreement.md
